alu.v
module alu(
    input [3:0]a, b, 
    input [1:0]select,
    output reg zero, carry, sign, parity, overflow,
    output reg [3:0]out
) ;

always @ (a or b) begin
    case (select)
        0 : {carry, out} = a + b ;
        1 : {carry, out} = a - b ;
        2 : {carry, out} = a * b ;
        3 : {carry, out} = a / b ;
    endcase
    zero = ~|out ;
    sign = out[3] ;
    parity = ~^out ;
    overflow = (a[3] & b[3] & ~out[3]) | (~a[3] & ~b[3] & out[3]) ;
end

endmodule

testbench.v
module testbench ;
    reg [3:0]a, b ;     //register declaration for a & b
    reg [1:0]select ;   //register declaration for select
    wire [3:0]out ;     //wire declaration for out
    wire zero, carry, sign, parity, overflow ; //wire declaration for zero, carry, sign, parity, overflow

    alu dut (.a(a), .b(b), .select(select), .zero(zero), .carry(carry), .sign(sign), .parity(parity), .overflow(overflow),.out(out));
    initial begin
        $dumpfile("testbench.vcd");
        $dumpvars(0,testbench);
        repeat(10) begin
            stimulus();#5;
            $display("a = %b, b = %b, select = %b, out = %b, zero = %b, carry = %b, sign =%b, parity = %b, overflow = %b", a, b, select, out, zero, carry, sign, parity, overflow);
        end
    end

    task stimulus; begin
            a = $random ;
            b = $random ;
            select = $random ;
        end
    endtask
endmodule

testbench.vcd
$date
	Tue Oct 10 17:59:04 2023
$end
$version
	Icarus Verilog
$end
$timescale
	1s
$end
$scope module testbench $end
$var wire 1 ! zero $end
$var wire 1 " sign $end
$var wire 1 # parity $end
$var wire 1 $ overflow $end
$var wire 4 % out [3:0] $end
$var wire 1 & carry $end
$var reg 4 ' a [3:0] $end
$var reg 4 ( b [3:0] $end
$var reg 2 ) select [1:0] $end
$scope module dut $end
$var wire 4 * a [3:0] $end
$var wire 4 + b [3:0] $end
$var wire 2 , select [1:0] $end
$var reg 1 & carry $end
$var reg 4 - out [3:0] $end
$var reg 1 $ overflow $end
$var reg 1 # parity $end
$var reg 1 " sign $end
$var reg 1 ! zero $end
$upscope $end
$scope task stimulus $end
$upscope $end
$upscope $end
$enddefinitions $end
$comment Show the parameter values. $end
$dumpall
$end
#0
$dumpvars
b11 -
b1 ,
b1 +
b100 *
b1 )
b1 (
b100 '
0&
b11 %
0$
1#
0"
0!
$end
#5
1&
b110 %
b110 -
b1101 (
b1101 +
b11 '
b11 *
#10
0&
b11 %
b11 -
b10 (
b10 +
b101 '
b101 *
#15
0#
b111 %
b111 -
b110 (
b110 +
b1101 '
b1101 *
#20
1$
b1 %
b1 -
b1100 (
b1100 +
#25
1"
1&
b1110 %
b1110 -
b10 )
b10 ,
b101 (
b101 +
b110 '
b110 *
#30
0$
1#
0"
0&
b11 %
b11 -
b111 (
b111 +
b101 '
b101 *
#35
0#
1"
1&
b1110 %
b1110 -
b10 (
b10 +
b1111 '
b1111 *
#40
0&
b1101 %
b1101 -
b0 )
b0 ,
b101 (
b101 +
b1000 '
b1000 *
#45
1$
1#
0"
1!
b0 %
b0 -
b1 )
b1 ,
b1101 (
b1101 +
b1101 '
b1101 *
